kintaiyi/__init__.py
kintaiyi/config.py
kintaiyi/jieqi.py
kintaiyi/kintaiyi.py
kintaiyi/taiyidict.py
kintaiyi-0.2.3.dist-info/METADATA
kintaiyi-0.2.3.dist-info/WHEEL
kintaiyi-0.2.3.dist-info/top_level.txt
kintaiyi-0.2.3.dist-info/RECORD
