Metadata-Version: 2.1
Name: kintaiyi
Version: 0.2.3
Summary: Taiyi(太乙) is one of the three greatest Chinese Divination systems (三式) ever. 
Home-page: https://github.com/kentang2017/kintaiyi
Author: Ken Tang
Author-email: kinyeah@gmail.com
Classifier: Programming Language :: Python :: 3
Classifier: License :: OSI Approved :: MIT License
Classifier: Operating System :: OS Independent
